Metadata-Version: 2.1
Name: override-pydantic-settings
Version: 1.0.0
Summary: Override pydantic settings
Home-page: https://github.com/na86421/override-pydantic-settings
Author: Junki Yoon
Author-email: na66421@gmai.com
License: UNKNOWN
Platform: UNKNOWN
Classifier: Programming Language :: Python :: 3
Classifier: License :: OSI Approved :: MIT License
Classifier: Operating System :: OS Independent
Requires-Python: >=3.6
